LICENSE
metadeco/__init__.py
metadeco/py.typed
README.md
metadeco-0.2.1.dist-info/LICENSE
metadeco-0.2.1.dist-info/WHEEL
metadeco-0.2.1.dist-info/METADATA
metadeco-0.2.1.dist-info/RECORD
